fpga/systolic_array_4x4/rtl/pe.sv
module pe #(
    parameter int WIDTH = 8
) (
    input  logic                    clk,
    input  logic                    rst,
    input  logic                    en,
    input  logic signed [WIDTH-1:0] a_in,
    input  logic signed [WIDTH-1:0] b_in,
    output logic signed [WIDTH-1:0] a_out,
    output logic signed [WIDTH-1:0] b_out,
    output logic signed [2*WIDTH-1:0] acc
);
    always_ff @(posedge clk) begin
        if (rst) begin
            a_out <= '0;
            b_out <= '0;
            acc   <= '0;
        end else if (en) begin
            a_out <= a_in;
            b_out <= b_in;
            acc   <= acc + (a_in * b_in);
        end
    end
endmodule

fpga/systolic_array_4x4/tb/dump.vcd
$version Generated by VerilatedVcd $end
$timescale 1ps $end
 $scope module $rootio $end
  $var wire 1 # clk $end
  $var wire 1 $ rst $end
  $var wire 1 % en $end
  $var wire 8 & a_in [7:0] $end
  $var wire 8 ' b_in [7:0] $end
  $var wire 8 ( a_out [7:0] $end
  $var wire 8 ) b_out [7:0] $end
  $var wire 16 * acc [15:0] $end
 $upscope $end
 $scope module pe $end
  $var wire 32 3 WIDTH [31:0] $end
  $var wire 1 + clk $end
  $var wire 1 , rst $end
  $var wire 1 - en $end
  $var wire 8 . a_in [7:0] $end
  $var wire 8 / b_in [7:0] $end
  $var wire 8 0 a_out [7:0] $end
  $var wire 8 1 b_out [7:0] $end
  $var wire 16 2 acc [15:0] $end
 $upscope $end
$enddefinitions $end


#0
1#
1$
0%
b00000000 &
b00000000 '
b00000000 (
b00000000 )
b0000000000000000 *
1+
1,
0-
b00000000 .
b00000000 /
b00000000 0
b00000000 1
b0000000000000000 2
b00000000000000000000000000001000 3
#5000
0#
0+
#10000
1#
1+
#15000
0#
0+
#20000
1#
0$
1%
b01000101 &
b10000111 '
1+
0,
1-
b01000101 .
b10000111 /
#25000
0#
0+
#30000
1#
b01000101 (
b10000111 )
b1101111101100011 *
1+
b01000101 0
b10000111 1
b1101111101100011 2
#31000
1$
0%
1,
0-
#35000
0#
0+
#40000
1#
0$
1%
b00101111 &
b10101101 '
b00000000 (
b00000000 )
b0000000000000000 *
1+
0,
1-
b00101111 .
b10101101 /
b00000000 0
b00000000 1
b0000000000000000 2
#45000
0#
0+
#50000
1#
b00101111 (
b10101101 )
b1111000011000011 *
1+
b00101111 0
b10101101 1
b1111000011000011 2
#51000
1$
0%
1,
0-
#55000
0#
0+
#60000
1#
0$
1%
b01011000 &
b11010010 '
b00000000 (
b00000000 )
b0000000000000000 *
1+
0,
1-
b01011000 .
b11010010 /
b00000000 0
b00000000 1
b0000000000000000 2
#65000
0#
0+
#70000
1#
b01011000 (
b11010010 )
b1111000000110000 *
1+
b01011000 0
b11010010 1
b1111000000110000 2
#71000
1$
0%
1,
0-
#75000
0#
0+
#80000
1#
0$
1%
b10100110 &
b01010001 '
b00000000 (
b00000000 )
b0000000000000000 *
1+
0,
1-
b10100110 .
b01010001 /
b00000000 0
b00000000 1
b0000000000000000 2
#85000
0#
0+
#90000
1#
b10100110 (
b01010001 )
b1110001110000110 *
1+
b10100110 0
b01010001 1
b1110001110000110 2
#91000
1$
0%
1,
0-
#95000
0#
0+
#100000
1#
0$
1%
b01001101 &
b01011101 '
b00000000 (
b00000000 )
b0000000000000000 *
1+
0,
1-
b01001101 .
b01011101 /
b00000000 0
b00000000 1
b0000000000000000 2
#105000
0#
0+
#110000
1#
b01001101 (
b01011101 )
b0001101111111001 *
1+
b01001101 0
b01011101 1
b0001101111111001 2
#111000
1$
0%
1,
0-
#115000
0#
0+
#120000
1#
0$
1%
b10100101 &
b11110000 '
b00000000 (
b00000000 )
b0000000000000000 *
1+
0,
1-
b10100101 .
b11110000 /
b00000000 0
b00000000 1
b0000000000000000 2
#125000
0#
0+
#130000
1#
b10100101 (
b11110000 )
b0000010110110000 *
1+
b10100101 0
b11110000 1
b0000010110110000 2
#131000
1$
0%
1,
0-
#135000
0#
0+
#140000
1#
0$
1%
b00110010 &
b00011110 '
b00000000 (
b00000000 )
b0000000000000000 *
1+
0,
1-
b00110010 .
b00011110 /
b00000000 0
b00000000 1
b0000000000000000 2
#145000
0#
0+
#150000
1#
b00110010 (
b00011110 )
b0000010111011100 *
1+
b00110010 0
b00011110 1
b0000010111011100 2
#151000
1$
0%
1,
0-
#155000
0#
0+
#160000
1#
0$
1%
b11110100 &
b11001010 '
b00000000 (
b00000000 )
b0000000000000000 *
1+
0,
1-
b11110100 .
b11001010 /
b00000000 0
b00000000 1
b0000000000000000 2
#165000
0#
0+
#170000
1#
b11110100 (
b11001010 )
b0000001010001000 *
1+
b11110100 0
b11001010 1
b0000001010001000 2
#171000
1$
0%
1,
0-
#175000
0#
0+
#180000
1#
0$
1%
b01000010 &
b11100101 '
b00000000 (
b00000000 )
b0000000000000000 *
1+
0,
1-
b01000010 .
b11100101 /
b00000000 0
b00000000 1
b0000000000000000 2
#185000
0#
0+
#190000
1#
b01000010 (
b11100101 )
b1111100100001010 *
1+
b01000010 0
b11100101 1
b1111100100001010 2
#191000
1$
0%
1,
0-
#195000
0#
0+
#200000
1#
0$
1%
b10100100 &
b00011110 '
b00000000 (
b00000000 )
b0000000000000000 *
1+
0,
1-
b10100100 .
b00011110 /
b00000000 0
b00000000 1
b0000000000000000 2
#205000
0#
0+
#210000
1#
b10100100 (
b00011110 )
b1111010100111000 *
1+
b10100100 0
b00011110 1
b1111010100111000 2
