fpga/systolic_array_4x4/rtl/pe.sv
module pe #(
    parameter int WIDTH = 8
) (
    input  logic                    clk,
    input  logic                    rst,
    input  logic                    en,
    input  logic signed [WIDTH-1:0] a_in,
    input  logic signed [WIDTH-1:0] b_in,
    output logic signed [WIDTH-1:0] a_out,
    output logic signed [WIDTH-1:0] b_out,
    output logic signed [2*WIDTH-1:0] acc
);
    always_ff @(posedge clk) begin
        if (rst) begin
            a_out <= '0;
            b_out <= '0;
            acc   <= '0;
        end else if (en) begin
            a_out <= a_in;
            b_out <= b_in;
            acc   <= acc + (a_in * b_in);
        end
    end
endmodule

fpga/systolic_array_4x4/rtl/systolic_array_4x4.sv
module systolic_array_4x4 #(
    parameter int WIDTH = 8
) (
    input  logic                     clk,
    input  logic                     rst,
    input  logic                     en,
    input  logic signed [WIDTH-1:0]  a_in [0:3],
    input  logic signed [WIDTH-1:0]  b_in [0:3],
    output logic signed [2*WIDTH-1:0] c_out [0:3][0:3]
);

    logic signed [WIDTH-1:0] a_wire [0:3][0:4];
    logic signed [WIDTH-1:0] b_wire [0:4][0:3];

    genvar i, j;
    generate
        for (i = 0; i < 4; i++) begin : g_a_in
            assign a_wire[i][0] = a_in[i];
        end
        for (j = 0; j < 4; j++) begin : g_b_in
            assign b_wire[0][j] = b_in[j];
        end
    endgenerate

    generate
        for (i = 0; i < 4; i++) begin : g_row
            for (j = 0; j < 4; j++) begin : g_col
                pe #(.WIDTH(WIDTH)) pe_inst (
                    .clk   (clk),
                    .rst   (rst),
                    .en    (en),
                    .a_in  (a_wire[i][j]),
                    .b_in  (b_wire[i][j]),
                    .a_out (a_wire[i][j+1]),
                    .b_out (b_wire[i+1][j]),
                    .acc   (c_out[i][j])
                );
            end
        end
    endgenerate

endmodule

fpga/systolic_array_4x4/tb/dump.vcd
$version Generated by VerilatedVcd $end
$timescale 1ps $end
 $scope module $rootio $end
  $var wire 1 # clk $end
  $var wire 1 $ rst $end
  $var wire 1 % en $end
 $upscope $end
 $var wire 8 & a_in[0] [7:0] $end
 $var wire 8 ' a_in[1] [7:0] $end
 $var wire 8 ( a_in[2] [7:0] $end
 $var wire 8 ) a_in[3] [7:0] $end
 $var wire 8 * b_in[0] [7:0] $end
 $var wire 8 + b_in[1] [7:0] $end
 $var wire 8 , b_in[2] [7:0] $end
 $var wire 8 - b_in[3] [7:0] $end
 $var wire 16 . c_out[0][0] [15:0] $end
 $var wire 16 / c_out[0][1] [15:0] $end
 $var wire 16 0 c_out[0][2] [15:0] $end
 $var wire 16 1 c_out[0][3] [15:0] $end
 $var wire 16 2 c_out[1][0] [15:0] $end
 $var wire 16 3 c_out[1][1] [15:0] $end
 $var wire 16 4 c_out[1][2] [15:0] $end
 $var wire 16 5 c_out[1][3] [15:0] $end
 $var wire 16 6 c_out[2][0] [15:0] $end
 $var wire 16 7 c_out[2][1] [15:0] $end
 $var wire 16 8 c_out[2][2] [15:0] $end
 $var wire 16 9 c_out[2][3] [15:0] $end
 $var wire 16 : c_out[3][0] [15:0] $end
 $var wire 16 ; c_out[3][1] [15:0] $end
 $var wire 16 < c_out[3][2] [15:0] $end
 $var wire 16 = c_out[3][3] [15:0] $end
 $scope module systolic_array_4x4 $end
  $var wire 32 E" WIDTH [31:0] $end
  $var wire 1 > clk $end
  $var wire 1 ? rst $end
  $var wire 1 @ en $end
  $var wire 8 A a_in[0] [7:0] $end
  $var wire 8 B a_in[1] [7:0] $end
  $var wire 8 C a_in[2] [7:0] $end
  $var wire 8 D a_in[3] [7:0] $end
  $var wire 8 E b_in[0] [7:0] $end
  $var wire 8 F b_in[1] [7:0] $end
  $var wire 8 G b_in[2] [7:0] $end
  $var wire 8 H b_in[3] [7:0] $end
  $var wire 16 I c_out[0][0] [15:0] $end
  $var wire 16 J c_out[0][1] [15:0] $end
  $var wire 16 K c_out[0][2] [15:0] $end
  $var wire 16 L c_out[0][3] [15:0] $end
  $var wire 16 M c_out[1][0] [15:0] $end
  $var wire 16 N c_out[1][1] [15:0] $end
  $var wire 16 O c_out[1][2] [15:0] $end
  $var wire 16 P c_out[1][3] [15:0] $end
  $var wire 16 Q c_out[2][0] [15:0] $end
  $var wire 16 R c_out[2][1] [15:0] $end
  $var wire 16 S c_out[2][2] [15:0] $end
  $var wire 16 T c_out[2][3] [15:0] $end
  $var wire 16 U c_out[3][0] [15:0] $end
  $var wire 16 V c_out[3][1] [15:0] $end
  $var wire 16 W c_out[3][2] [15:0] $end
  $var wire 16 X c_out[3][3] [15:0] $end
  $var wire 8 Y a_wire[0][0] [7:0] $end
  $var wire 8 Z a_wire[0][1] [7:0] $end
  $var wire 8 [ a_wire[0][2] [7:0] $end
  $var wire 8 \ a_wire[0][3] [7:0] $end
  $var wire 8 ] a_wire[0][4] [7:0] $end
  $var wire 8 ^ a_wire[1][0] [7:0] $end
  $var wire 8 _ a_wire[1][1] [7:0] $end
  $var wire 8 ` a_wire[1][2] [7:0] $end
  $var wire 8 a a_wire[1][3] [7:0] $end
  $var wire 8 b a_wire[1][4] [7:0] $end
  $var wire 8 c a_wire[2][0] [7:0] $end
  $var wire 8 d a_wire[2][1] [7:0] $end
  $var wire 8 e a_wire[2][2] [7:0] $end
  $var wire 8 f a_wire[2][3] [7:0] $end
  $var wire 8 g a_wire[2][4] [7:0] $end
  $var wire 8 h a_wire[3][0] [7:0] $end
  $var wire 8 i a_wire[3][1] [7:0] $end
  $var wire 8 j a_wire[3][2] [7:0] $end
  $var wire 8 k a_wire[3][3] [7:0] $end
  $var wire 8 l a_wire[3][4] [7:0] $end
  $var wire 8 m b_wire[0][0] [7:0] $end
  $var wire 8 n b_wire[0][1] [7:0] $end
  $var wire 8 o b_wire[0][2] [7:0] $end
  $var wire 8 p b_wire[0][3] [7:0] $end
  $var wire 8 q b_wire[1][0] [7:0] $end
  $var wire 8 r b_wire[1][1] [7:0] $end
  $var wire 8 s b_wire[1][2] [7:0] $end
  $var wire 8 t b_wire[1][3] [7:0] $end
  $var wire 8 u b_wire[2][0] [7:0] $end
  $var wire 8 v b_wire[2][1] [7:0] $end
  $var wire 8 w b_wire[2][2] [7:0] $end
  $var wire 8 x b_wire[2][3] [7:0] $end
  $var wire 8 y b_wire[3][0] [7:0] $end
  $var wire 8 z b_wire[3][1] [7:0] $end
  $var wire 8 { b_wire[3][2] [7:0] $end
  $var wire 8 | b_wire[3][3] [7:0] $end
  $var wire 8 } b_wire[4][0] [7:0] $end
  $var wire 8 ~ b_wire[4][1] [7:0] $end
  $var wire 8 !! b_wire[4][2] [7:0] $end
  $var wire 8 "! b_wire[4][3] [7:0] $end
  $scope module g_row[0] $end
   $scope module g_col[0] $end
    $scope module pe_inst $end
     $var wire 32 E" WIDTH [31:0] $end
     $var wire 1 #! clk $end
     $var wire 1 $! rst $end
     $var wire 1 %! en $end
     $var wire 8 &! a_in [7:0] $end
     $var wire 8 '! b_in [7:0] $end
     $var wire 8 (! a_out [7:0] $end
     $var wire 8 )! b_out [7:0] $end
     $var wire 16 *! acc [15:0] $end
    $upscope $end
   $upscope $end
   $scope module g_col[1] $end
    $scope module pe_inst $end
     $var wire 32 E" WIDTH [31:0] $end
     $var wire 1 +! clk $end
     $var wire 1 ,! rst $end
     $var wire 1 -! en $end
     $var wire 8 .! a_in [7:0] $end
     $var wire 8 /! b_in [7:0] $end
     $var wire 8 0! a_out [7:0] $end
     $var wire 8 1! b_out [7:0] $end
     $var wire 16 2! acc [15:0] $end
    $upscope $end
   $upscope $end
   $scope module g_col[2] $end
    $scope module pe_inst $end
     $var wire 32 E" WIDTH [31:0] $end
     $var wire 1 3! clk $end
     $var wire 1 4! rst $end
     $var wire 1 5! en $end
     $var wire 8 6! a_in [7:0] $end
     $var wire 8 7! b_in [7:0] $end
     $var wire 8 8! a_out [7:0] $end
     $var wire 8 9! b_out [7:0] $end
     $var wire 16 :! acc [15:0] $end
    $upscope $end
   $upscope $end
   $scope module g_col[3] $end
    $scope module pe_inst $end
     $var wire 32 E" WIDTH [31:0] $end
     $var wire 1 ;! clk $end
     $var wire 1 <! rst $end
     $var wire 1 =! en $end
     $var wire 8 >! a_in [7:0] $end
     $var wire 8 ?! b_in [7:0] $end
     $var wire 8 @! a_out [7:0] $end
     $var wire 8 A! b_out [7:0] $end
     $var wire 16 B! acc [15:0] $end
    $upscope $end
   $upscope $end
  $upscope $end
  $scope module g_row[1] $end
   $scope module g_col[0] $end
    $scope module pe_inst $end
     $var wire 32 E" WIDTH [31:0] $end
     $var wire 1 C! clk $end
     $var wire 1 D! rst $end
     $var wire 1 E! en $end
     $var wire 8 F! a_in [7:0] $end
     $var wire 8 G! b_in [7:0] $end
     $var wire 8 H! a_out [7:0] $end
     $var wire 8 I! b_out [7:0] $end
     $var wire 16 J! acc [15:0] $end
    $upscope $end
   $upscope $end
   $scope module g_col[1] $end
    $scope module pe_inst $end
     $var wire 32 E" WIDTH [31:0] $end
     $var wire 1 K! clk $end
     $var wire 1 L! rst $end
     $var wire 1 M! en $end
     $var wire 8 N! a_in [7:0] $end
     $var wire 8 O! b_in [7:0] $end
     $var wire 8 P! a_out [7:0] $end
     $var wire 8 Q! b_out [7:0] $end
     $var wire 16 R! acc [15:0] $end
    $upscope $end
   $upscope $end
   $scope module g_col[2] $end
    $scope module pe_inst $end
     $var wire 32 E" WIDTH [31:0] $end
     $var wire 1 S! clk $end
     $var wire 1 T! rst $end
     $var wire 1 U! en $end
     $var wire 8 V! a_in [7:0] $end
     $var wire 8 W! b_in [7:0] $end
     $var wire 8 X! a_out [7:0] $end
     $var wire 8 Y! b_out [7:0] $end
     $var wire 16 Z! acc [15:0] $end
    $upscope $end
   $upscope $end
   $scope module g_col[3] $end
    $scope module pe_inst $end
     $var wire 32 E" WIDTH [31:0] $end
     $var wire 1 [! clk $end
     $var wire 1 \! rst $end
     $var wire 1 ]! en $end
     $var wire 8 ^! a_in [7:0] $end
     $var wire 8 _! b_in [7:0] $end
     $var wire 8 `! a_out [7:0] $end
     $var wire 8 a! b_out [7:0] $end
     $var wire 16 b! acc [15:0] $end
    $upscope $end
   $upscope $end
  $upscope $end
  $scope module g_row[2] $end
   $scope module g_col[0] $end
    $scope module pe_inst $end
     $var wire 32 E" WIDTH [31:0] $end
     $var wire 1 c! clk $end
     $var wire 1 d! rst $end
     $var wire 1 e! en $end
     $var wire 8 f! a_in [7:0] $end
     $var wire 8 g! b_in [7:0] $end
     $var wire 8 h! a_out [7:0] $end
     $var wire 8 i! b_out [7:0] $end
     $var wire 16 j! acc [15:0] $end
    $upscope $end
   $upscope $end
   $scope module g_col[1] $end
    $scope module pe_inst $end
     $var wire 32 E" WIDTH [31:0] $end
     $var wire 1 k! clk $end
     $var wire 1 l! rst $end
     $var wire 1 m! en $end
     $var wire 8 n! a_in [7:0] $end
     $var wire 8 o! b_in [7:0] $end
     $var wire 8 p! a_out [7:0] $end
     $var wire 8 q! b_out [7:0] $end
     $var wire 16 r! acc [15:0] $end
    $upscope $end
   $upscope $end
   $scope module g_col[2] $end
    $scope module pe_inst $end
     $var wire 32 E" WIDTH [31:0] $end
     $var wire 1 s! clk $end
     $var wire 1 t! rst $end
     $var wire 1 u! en $end
     $var wire 8 v! a_in [7:0] $end
     $var wire 8 w! b_in [7:0] $end
     $var wire 8 x! a_out [7:0] $end
     $var wire 8 y! b_out [7:0] $end
     $var wire 16 z! acc [15:0] $end
    $upscope $end
   $upscope $end
   $scope module g_col[3] $end
    $scope module pe_inst $end
     $var wire 32 E" WIDTH [31:0] $end
     $var wire 1 {! clk $end
     $var wire 1 |! rst $end
     $var wire 1 }! en $end
     $var wire 8 ~! a_in [7:0] $end
     $var wire 8 !" b_in [7:0] $end
     $var wire 8 "" a_out [7:0] $end
     $var wire 8 #" b_out [7:0] $end
     $var wire 16 $" acc [15:0] $end
    $upscope $end
   $upscope $end
  $upscope $end
  $scope module g_row[3] $end
   $scope module g_col[0] $end
    $scope module pe_inst $end
     $var wire 32 E" WIDTH [31:0] $end
     $var wire 1 %" clk $end
     $var wire 1 &" rst $end
     $var wire 1 '" en $end
     $var wire 8 (" a_in [7:0] $end
     $var wire 8 )" b_in [7:0] $end
     $var wire 8 *" a_out [7:0] $end
     $var wire 8 +" b_out [7:0] $end
     $var wire 16 ," acc [15:0] $end
    $upscope $end
   $upscope $end
   $scope module g_col[1] $end
    $scope module pe_inst $end
     $var wire 32 E" WIDTH [31:0] $end
     $var wire 1 -" clk $end
     $var wire 1 ." rst $end
     $var wire 1 /" en $end
     $var wire 8 0" a_in [7:0] $end
     $var wire 8 1" b_in [7:0] $end
     $var wire 8 2" a_out [7:0] $end
     $var wire 8 3" b_out [7:0] $end
     $var wire 16 4" acc [15:0] $end
    $upscope $end
   $upscope $end
   $scope module g_col[2] $end
    $scope module pe_inst $end
     $var wire 32 E" WIDTH [31:0] $end
     $var wire 1 5" clk $end
     $var wire 1 6" rst $end
     $var wire 1 7" en $end
     $var wire 8 8" a_in [7:0] $end
     $var wire 8 9" b_in [7:0] $end
     $var wire 8 :" a_out [7:0] $end
     $var wire 8 ;" b_out [7:0] $end
     $var wire 16 <" acc [15:0] $end
    $upscope $end
   $upscope $end
   $scope module g_col[3] $end
    $scope module pe_inst $end
     $var wire 32 E" WIDTH [31:0] $end
     $var wire 1 =" clk $end
     $var wire 1 >" rst $end
     $var wire 1 ?" en $end
     $var wire 8 @" a_in [7:0] $end
     $var wire 8 A" b_in [7:0] $end
     $var wire 8 B" a_out [7:0] $end
     $var wire 8 C" b_out [7:0] $end
     $var wire 16 D" acc [15:0] $end
    $upscope $end
   $upscope $end
  $upscope $end
 $upscope $end
$enddefinitions $end


#0
1#
1$
0%
b00000000 &
b00000000 '
b00000000 (
b00000000 )
b00000000 *
b00000000 +
b00000000 ,
b00000000 -
b0000000000000000 .
b0000000000000000 /
b0000000000000000 0
b0000000000000000 1
b0000000000000000 2
b0000000000000000 3
b0000000000000000 4
b0000000000000000 5
b0000000000000000 6
b0000000000000000 7
b0000000000000000 8
b0000000000000000 9
b0000000000000000 :
b0000000000000000 ;
b0000000000000000 <
b0000000000000000 =
1>
1?
0@
b00000000 A
b00000000 B
b00000000 C
b00000000 D
b00000000 E
b00000000 F
b00000000 G
b00000000 H
b0000000000000000 I
b0000000000000000 J
b0000000000000000 K
b0000000000000000 L
b0000000000000000 M
b0000000000000000 N
b0000000000000000 O
b0000000000000000 P
b0000000000000000 Q
b0000000000000000 R
b0000000000000000 S
b0000000000000000 T
b0000000000000000 U
b0000000000000000 V
b0000000000000000 W
b0000000000000000 X
b00000000 Y
b00000000 Z
b00000000 [
b00000000 \
b00000000 ]
b00000000 ^
b00000000 _
b00000000 `
b00000000 a
b00000000 b
b00000000 c
b00000000 d
b00000000 e
b00000000 f
b00000000 g
b00000000 h
b00000000 i
b00000000 j
b00000000 k
b00000000 l
b00000000 m
b00000000 n
b00000000 o
b00000000 p
b00000000 q
b00000000 r
b00000000 s
b00000000 t
b00000000 u
b00000000 v
b00000000 w
b00000000 x
b00000000 y
b00000000 z
b00000000 {
b00000000 |
b00000000 }
b00000000 ~
b00000000 !!
b00000000 "!
1#!
1$!
0%!
b00000000 &!
b00000000 '!
b00000000 (!
b00000000 )!
b0000000000000000 *!
1+!
1,!
0-!
b00000000 .!
b00000000 /!
b00000000 0!
b00000000 1!
b0000000000000000 2!
13!
14!
05!
b00000000 6!
b00000000 7!
b00000000 8!
b00000000 9!
b0000000000000000 :!
1;!
1<!
0=!
b00000000 >!
b00000000 ?!
b00000000 @!
b00000000 A!
b0000000000000000 B!
1C!
1D!
0E!
b00000000 F!
b00000000 G!
b00000000 H!
b00000000 I!
b0000000000000000 J!
1K!
1L!
0M!
b00000000 N!
b00000000 O!
b00000000 P!
b00000000 Q!
b0000000000000000 R!
1S!
1T!
0U!
b00000000 V!
b00000000 W!
b00000000 X!
b00000000 Y!
b0000000000000000 Z!
1[!
1\!
0]!
b00000000 ^!
b00000000 _!
b00000000 `!
b00000000 a!
b0000000000000000 b!
1c!
1d!
0e!
b00000000 f!
b00000000 g!
b00000000 h!
b00000000 i!
b0000000000000000 j!
1k!
1l!
0m!
b00000000 n!
b00000000 o!
b00000000 p!
b00000000 q!
b0000000000000000 r!
1s!
1t!
0u!
b00000000 v!
b00000000 w!
b00000000 x!
b00000000 y!
b0000000000000000 z!
1{!
1|!
0}!
b00000000 ~!
b00000000 !"
b00000000 ""
b00000000 #"
b0000000000000000 $"
1%"
1&"
0'"
b00000000 ("
b00000000 )"
b00000000 *"
b00000000 +"
b0000000000000000 ,"
1-"
1."
0/"
b00000000 0"
b00000000 1"
b00000000 2"
b00000000 3"
b0000000000000000 4"
15"
16"
07"
b00000000 8"
b00000000 9"
b00000000 :"
b00000000 ;"
b0000000000000000 <"
1="
1>"
0?"
b00000000 @"
b00000000 A"
b00000000 B"
b00000000 C"
b0000000000000000 D"
b00000000000000000000000000001000 E"
#5000
0#
0>
0#!
0+!
03!
0;!
0C!
0K!
0S!
0[!
0c!
0k!
0s!
0{!
0%"
0-"
05"
0="
#10000
1#
0$
1%
b10001010 &
b11101000 *
1>
0?
1@
b10001010 A
b11101000 E
b10001010 Y
b11101000 m
1#!
0$!
1%!
b10001010 &!
b11101000 '!
1+!
0,!
1-!
13!
04!
15!
1;!
0<!
1=!
1C!
0D!
1E!
1K!
0L!
1M!
1S!
0T!
1U!
1[!
0\!
1]!
1c!
0d!
1e!
1k!
0l!
1m!
1s!
0t!
1u!
1{!
0|!
1}!
1%"
0&"
1'"
1-"
0."
1/"
15"
06"
17"
1="
0>"
1?"
#15000
0#
0>
0#!
0+!
03!
0;!
0C!
0K!
0S!
0[!
0c!
0k!
0s!
0{!
0%"
0-"
05"
0="
#20000
1#
b0000101100010000 .
1>
b0000101100010000 I
b10001010 Z
b11101000 q
1#!
b10001010 (!
b11101000 )!
b0000101100010000 *!
1+!
b10001010 .!
13!
1;!
1C!
b11101000 G!
1K!
1S!
1[!
1c!
1k!
1s!
1{!
1%"
1-"
15"
1="
#21000
b00010011 &
b01011111 '
b00010001 *
b11110101 +
b00010011 A
b01011111 B
b00010001 E
b11110101 F
b00010011 Y
b01011111 ^
b00010001 m
b11110101 n
b00010011 &!
b00010001 '!
b11110101 /!
b01011111 F!
#25000
0#
0>
0#!
0+!
03!
0;!
0C!
0K!
0S!
0[!
0c!
0k!
0s!
0{!
0%"
0-"
05"
0="
#30000
1#
b0000110001010011 .
b0000010100010010 /
b1111011100011000 2
1>
b0000110001010011 I
b0000010100010010 J
b1111011100011000 M
b00010011 Z
b10001010 [
b01011111 _
b00010001 q
b11110101 r
b11101000 u
1#!
b00010011 (!
b00010001 )!
b0000110001010011 *!
1+!
b00010011 .!
b10001010 0!
b11110101 1!
b0000010100010010 2!
13!
b10001010 6!
1;!
1C!
b00010001 G!
b01011111 H!
b11101000 I!
b1111011100011000 J!
1K!
b01011111 N!
b11110101 O!
1S!
1[!
1c!
b11101000 g!
1k!
1s!
1{!
1%"
1-"
15"
1="
#31000
b10001110 &
b01001000 '
b11101000 (
b00000000 *
b11100101 +
b10000010 ,
b10001110 A
b01001000 B
b11101000 C
b00000000 E
b11100101 F
b10000010 G
b10001110 Y
b01001000 ^
b11101000 c
b00000000 m
b11100101 n
b10000010 o
b10001110 &!
b00000000 '!
b11100101 /!
b10000010 7!
b01001000 F!
b11101000 f!
#35000
0#
0>
0#!
0+!
03!
0;!
0C!
0K!
0S!
0[!
0c!
0k!
0s!
0{!
0%"
0-"
05"
0="
#40000
1#
b0000001100010001 /
b0011101000010100 0
b1111101111100000 2
b1111101111101011 3
b0000001001000000 6
1>
b0000001100010001 J
b0011101000010100 K
b1111101111100000 M
b1111101111101011 N
b0000001001000000 Q
b10001110 Z
b00010011 [
b10001010 \
b01001000 _
b01011111 `
b11101000 d
b00000000 q
b11100101 r
b10000010 s
b00010001 u
b11110101 v
b11101000 y
1#!
b10001110 (!
b00000000 )!
1+!
b10001110 .!
b00010011 0!
b11100101 1!
b0000001100010001 2!
13!
b00010011 6!
b10001010 8!
b10000010 9!
b0011101000010100 :!
1;!
b10001010 >!
1C!
b00000000 G!
b01001000 H!
b00010001 I!
b1111101111100000 J!
1K!
b01001000 N!
b11100101 O!
b01011111 P!
b11110101 Q!
b1111101111101011 R!
1S!
b01011111 V!
b10000010 W!
1[!
1c!
b00010001 g!
b11101000 h!
b11101000 i!
b0000001001000000 j!
1k!
b11101000 n!
b11110101 o!
1s!
1{!
1%"
b11101000 )"
1-"
15"
1="
#41000
b00011010 &
b00011011 '
b01111111 (
b10000000 )
b10000100 *
b10111100 +
b01000101 ,
b11100001 -
b00011010 A
b00011011 B
b01111111 C
b10000000 D
b10000100 E
b10111100 F
b01000101 G
b11100001 H
b00011010 Y
b00011011 ^
b01111111 c
b10000000 h
b10000100 m
b10111100 n
b01000101 o
b11100001 p
b00011010 &!
b10000100 '!
b10111100 /!
b01000101 7!
b11100001 ?!
b00011011 F!
b01111111 f!
b10000000 ("
#45000
0#
0>
0#!
0+!
03!
0;!
0C!
0K!
0S!
0[!
0c!
0k!
0s!
0{!
0%"
0-"
05"
0="
#50000
1#
b1111111110111011 .
b0010000101011001 /
b0011111100110011 0
b0000111001001010 1
b1111010001010011 3
b1101000100111110 4
b0000101010101111 6
b0000000100001000 7
b0000110000000000 :
1>
b1111111110111011 I
b0010000101011001 J
b0011111100110011 K
b0000111001001010 L
b1111010001010011 N
b1101000100111110 O
b0000101010101111 Q
b0000000100001000 R
b0000110000000000 U
b00011010 Z
b10001110 [
b00010011 \
b10001010 ]
b00011011 _
b01001000 `
b01011111 a
b01111111 d
b11101000 e
b10000000 i
b10000100 q
b10111100 r
b01000101 s
b11100001 t
b00000000 u
b11100101 v
b10000010 w
b00010001 y
b11110101 z
b11101000 }
1#!
b00011010 (!
b10000100 )!
b1111111110111011 *!
1+!
b00011010 .!
b10001110 0!
b10111100 1!
b0010000101011001 2!
13!
b10001110 6!
b00010011 8!
b01000101 9!
b0011111100110011 :!
1;!
b00010011 >!
b10001010 @!
b11100001 A!
b0000111001001010 B!
1C!
b10000100 G!
b00011011 H!
b00000000 I!
1K!
b00011011 N!
b10111100 O!
b01001000 P!
b11100101 Q!
b1111010001010011 R!
1S!
b01001000 V!
b01000101 W!
b01011111 X!
b10000010 Y!
b1101000100111110 Z!
1[!
b01011111 ^!
b11100001 _!
1c!
b00000000 g!
b01111111 h!
b00010001 i!
b0000101010101111 j!
1k!
b01111111 n!
b11100101 o!
b11101000 p!
b11110101 q!
b0000000100001000 r!
1s!
b11101000 v!
b10000010 w!
1{!
1%"
b00010001 )"
b10000000 *"
b11101000 +"
b0000110000000000 ,"
1-"
b10000000 0"
b11110101 1"
15"
1="
#51000
b00000000 &
b10010011 '
b01001011 (
b10110100 )
b00000000 *
b00100000 +
b00100010 ,
b11000100 -
b00000000 A
b10010011 B
b01001011 C
b10110100 D
b00000000 E
b00100000 F
b00100010 G
b11000100 H
b00000000 Y
b10010011 ^
b01001011 c
b10110100 h
b00000000 m
b00100000 n
b00100010 o
b11000100 p
b00000000 &!
b00000000 '!
b00100000 /!
b00100010 7!
b11000100 ?!
b10010011 F!
b01001011 f!
b10110100 ("
#55000
0#
0>
0#!
0+!
03!
0;!
0C!
0K!
0S!
0[!
0c!
0k!
0s!
0{!
0%"
0-"
05"
0="
#60000
1#
b0010010010011001 /
b0011000000001111 0
b0000100111010110 1
b0011000010101100 2
b1110110100100111 3
b1110010010100110 4
b1111010001111111 5
b1111001110100011 7
b0000101111010000 8
b0000011011110100 :
b0000010110000000 ;
1>
b0010010010011001 J
b0011000000001111 K
b0000100111010110 L
b0011000010101100 M
b1110110100100111 N
b1110010010100110 O
b1111010001111111 P
b1111001110100011 R
b0000101111010000 S
b0000011011110100 U
b0000010110000000 V
b00000000 Z
b00011010 [
b10001110 \
b00010011 ]
b10010011 _
b00011011 `
b01001000 a
b01011111 b
b01001011 d
b01111111 e
b11101000 f
b10110100 i
b10000000 j
b00000000 q
b00100000 r
b00100010 s
b11000100 t
b10000100 u
b10111100 v
b01000101 w
b11100001 x
b00000000 y
b11100101 z
b10000010 {
b00010001 }
b11110101 ~
1#!
b00000000 (!
b00000000 )!
1+!
b00000000 .!
b00011010 0!
b00100000 1!
b0010010010011001 2!
13!
b00011010 6!
b10001110 8!
b00100010 9!
b0011000000001111 :!
1;!
b10001110 >!
b00010011 @!
b11000100 A!
b0000100111010110 B!
1C!
b00000000 G!
b10010011 H!
b10000100 I!
b0011000010101100 J!
1K!
b10010011 N!
b00100000 O!
b00011011 P!
b10111100 Q!
b1110110100100111 R!
1S!
b00011011 V!
b00100010 W!
b01001000 X!
b01000101 Y!
b1110010010100110 Z!
1[!
b01001000 ^!
b11000100 _!
b01011111 `!
b11100001 a!
b1111010001111111 b!
1c!
b10000100 g!
b01001011 h!
b00000000 i!
1k!
b01001011 n!
b10111100 o!
b01111111 p!
b11100101 q!
b1111001110100011 r!
1s!
b01111111 v!
b01000101 w!
b11101000 x!
b10000010 y!
b0000101111010000 z!
1{!
b11101000 ~!
b11100001 !"
1%"
b00000000 )"
b10110100 *"
b00010001 +"
b0000011011110100 ,"
1-"
b10110100 0"
b11100101 1"
b10000000 2"
b11110101 3"
b0000010110000000 4"
15"
b10000000 8"
b10000010 9"
1="
#61000
b00000000 '
b00101010 (
b11100110 )
b00000000 +
b00011000 ,
b11100000 -
b00000000 B
b00101010 C
b11100110 D
b00000000 F
b00011000 G
b11100000 H
b00000000 ^
b00101010 c
b11100110 h
b00000000 n
b00011000 o
b11100000 p
b00000000 /!
b00011000 7!
b11100000 ?!
b00000000 F!
b00101010 f!
b11100110 ("
#65000
0#
0>
0#!
0+!
03!
0;!
0C!
0K!
0S!
0[!
0c!
0k!
0s!
0{!
0%"
0-"
05"
0="
#70000
1#
b0011001001111111 0
b0001100000010110 1
b1101111110000111 3
b1110100000111100 4
b1110001110011111 5
b1111011001010111 6
b1101111110110111 7
b0010111000001011 8
b0000001011101000 9
b0000110110000100 ;
b0011111100000000 <
1>
b0011001001111111 K
b0001100000010110 L
b1101111110000111 N
b1110100000111100 O
b1110001110011111 P
b1111011001010111 Q
b1101111110110111 R
b0010111000001011 S
b0000001011101000 T
b0000110110000100 V
b0011111100000000 W
b00000000 [
b00011010 \
b10001110 ]
b00000000 _
b10010011 `
b00011011 a
b01001000 b
b00101010 d
b01001011 e
b01111111 f
b11101000 g
b11100110 i
b10110100 j
b10000000 k
b00000000 r
b00011000 s
b11100000 t
b00000000 u
b00100000 v
b00100010 w
b11000100 x
b10000100 y
b10111100 z
b01000101 {
b11100001 |
b00000000 }
b11100101 ~
b10000010 !!
1#!
1+!
b00000000 0!
b00000000 1!
13!
b00000000 6!
b00011010 8!
b00011000 9!
b0011001001111111 :!
1;!
b00011010 >!
b10001110 @!
b11100000 A!
b0001100000010110 B!
1C!
b00000000 H!
b00000000 I!
1K!
b00000000 N!
b00000000 O!
b10010011 P!
b00100000 Q!
b1101111110000111 R!
1S!
b10010011 V!
b00011000 W!
b00011011 X!
b00100010 Y!
b1110100000111100 Z!
1[!
b00011011 ^!
b11100000 _!
b01001000 `!
b11000100 a!
b1110001110011111 b!
1c!
b00000000 g!
b00101010 h!
b10000100 i!
b1111011001010111 j!
1k!
b00101010 n!
b00100000 o!
b01001011 p!
b10111100 q!
b1101111110110111 r!
1s!
b01001011 v!
b00100010 w!
b01111111 x!
b01000101 y!
b0010111000001011 z!
1{!
b01111111 ~!
b11000100 !"
b11101000 ""
b11100001 #"
b0000001011101000 $"
1%"
b10000100 )"
b11100110 *"
b00000000 +"
1-"
b11100110 0"
b10111100 1"
b10110100 2"
b11100101 3"
b0000110110000100 4"
15"
b10110100 8"
b01000101 9"
b10000000 :"
b10000010 ;"
b0011111100000000 <"
1="
b10000000 @"
b11100001 A"
#71000
b00000000 (
b10001100 )
b00000000 ,
b11000110 -
b00000000 C
b10001100 D
b00000000 G
b11000110 H
b00000000 c
b10001100 h
b00000000 o
b11000110 p
b00000000 7!
b11000110 ?!
b00000000 f!
b10001100 ("
#75000
0#
0>
0#!
0+!
03!
0;!
0C!
0K!
0S!
0[!
0c!
0k!
0s!
0{!
0%"
0-"
05"
0="
